birdpressure/AnalBarber.py
birdpressure/AnalWilbeck.py
birdpressure/Bird.py
birdpressure/EOS.py
birdpressure/GridGenerator.py
birdpressure/ImpactScenario.py
birdpressure/Timing.py
birdpressure/__init__.py
birdpressure/version.py
birdpressure-0.0.2.data/data/LICENSE
birdpressure-0.0.2.data/data/README.md
birdpressure-0.0.2.dist-info/LICENSE
birdpressure-0.0.2.dist-info/METADATA
birdpressure-0.0.2.dist-info/WHEEL
birdpressure-0.0.2.dist-info/top_level.txt
birdpressure-0.0.2.dist-info/RECORD
